{
	"events": [
		{
			"background": "res://backgrounds/labDeuxiemeChapitre.jpg"
		},
		{
			"action": "join",
			"character": "character-1649340198.json",
			"mirror": false,
			"portrait": "Default",
			"position": {
				"0": false,
				"1": false,
				"2": false,
				"3": false,
				"4": false
			}
		},
		{
			"action": "join",
			"character": "character-1647770931.json",
			"mirror": false,
			"portrait": "Default",
			"position": {
				"0": false,
				"1": false,
				"2": true,
				"3": false,
				"4": false
			}
		},
		{
			"character": "character-1647770931.json",
			"options": [

			],
			"portrait": "",
			"question": "Alors Baptiste, ça donne quoi ces recherches ?"
		},
		{
			"choice": "Expliquer que le Zirgouflon à l'air d'être cancérigène",
			"condition": "",
			"definition": "",
			"value": ""
		},
		{
			"definition": "1649341783-648",
			"operation": "=",
			"set_value": "20"
		},
		{
			"character": "character-1649340198.json",
			"portrait": "",
			"text": "D'après mes recherches, ce produit semble cancérigène dans certains cas, il me faut effectuer plus de tests pour pouvoir conclure."
		},
		{
			"choice": "Affirmer que ce produit est cancérigène",
			"condition": "",
			"definition": "",
			"value": ""
		},
		{
			"definition": "1649341783-648",
			"operation": "=",
			"set_value": "50"
		},
		{
			"character": "",
			"portrait": "",
			"text": "Le Zirgouflon est bel et bien cancérigène, il faut donc bien faire attention à son utilisation ! Le taux obtenu reste néanmoins assez bas."
		},
		{
			"choice": "Ne pas se prononcer pour le moment",
			"condition": "",
			"definition": "",
			"value": ""
		},
		{
			"character": "",
			"portrait": "",
			"text": "Je n'ai rien de concluant pour le moment, je dois poursuivre encore mes tests..."
		},
		{
			"endbranch": ""
		}
	],
	"metadata": {
		"dialogic-version": "1.2",
		"file": "timeline-1649341147.json",
		"name": "II_2_3_lab_3_mois_plus_tard"
	}
}
